mmath/__init__.py
mmath-1.0.5.dist-info/LICENCE
mmath-1.0.5.dist-info/METADATA
mmath-1.0.5.dist-info/WHEEL
mmath-1.0.5.dist-info/top_level.txt
mmath-1.0.5.dist-info/RECORD
