Metadata-Version: 2.1
Name: mmath
Version: 1.0.5
Summary: Un simple module mathématique pour calculer le sinus d'un réel avec précision.
Home-page: https://github.com/Atepir/analyse-groupe-25
Author: Groupe 25
Author-email: analyse25info@gmail.com
License: UNKNOWN
Project-URL: Bug Tracker, https://github.com/Atepir/analyse-groupe-25/issues
Platform: UNKNOWN
Classifier: Programming Language :: Python :: 3
Classifier: License :: OSI Approved :: MIT License
Classifier: Operating System :: OS Independent
Requires-Python: >=3.0
